pathlib2/__init__.py
pathlib2-2.3.7.post0.dist-info/LICENSE.rst
pathlib2-2.3.7.post0.dist-info/METADATA
pathlib2-2.3.7.post0.dist-info/WHEEL
pathlib2-2.3.7.post0.dist-info/top_level.txt
pathlib2-2.3.7.post0.dist-info/RECORD
