Metadata-Version: 2.1
Name: pathlib2
Version: 2.3.7.post0
Summary: Object-oriented filesystem paths
Home-page: https://github.com/jazzband/pathlib2
Author: Matthias C. M. Troffaes
Author-email: matthias.troffaes@gmail.com
License: MIT
Platform: UNKNOWN
Classifier: Development Status :: 5 - Production/Stable
Classifier: Intended Audience :: Developers
Classifier: License :: OSI Approved :: MIT License
Classifier: Operating System :: OS Independent
Classifier: Programming Language :: Python
Classifier: Programming Language :: Python :: 2
Classifier: Programming Language :: Python :: 3
Classifier: Programming Language :: Python :: 2.7
Classifier: Programming Language :: Python :: 3.5
Classifier: Programming Language :: Python :: 3.6
Classifier: Programming Language :: Python :: 3.7
Classifier: Programming Language :: Python :: 3.8
Classifier: Programming Language :: Python :: 3.9
Classifier: Topic :: Software Development :: Libraries
Classifier: Topic :: System :: Filesystems
Requires-Dist: six (>=1.13.0)
Requires-Dist: scandir ; python_version<"3.5"
Requires-Dist: typing ; python_version<"3.5"
